{
  "resource": "/latest",
  "path": "/latest",
  "httpMethod": "GET",
  "headers": {
    "Accept": "*/*",
    "Accept-Encoding": "gzip, deflate, br",
    "Accept-Language": "en-GB,en;q=0.8,en-US;q=0.6",
    "cache-control": "no-cache",
    "CloudFront-Forwarded-Proto": "https",
    "CloudFront-Is-Desktop-Viewer": "true",
    "CloudFront-Is-Mobile-Viewer": "false",
    "CloudFront-Is-SmartTV-Viewer": "false",
    "CloudFront-Is-Tablet-Viewer": "false",
    "CloudFront-Viewer-Country": "GB",
    "Host": "jqs5f5wrsh.execute-api.eu-west-1.amazonaws.com",
    "postman-token": "0e5a5f11-af61-2478-72b0-a7fc3f1eb5a7",
    "User-Agent":
      "Mozilla/5.0 (Macintosh; Intel Mac OS X 10_12_6) AppleWebKit/537.36 (KHTML, like Gecko) Chrome/61.0.3163.100 Safari/537.36",
    "Via": "2.0 bc30b374b64a194ed68c5b62e617bac6.cloudfront.net (CloudFront)",
    "X-Amz-Cf-Id": "DUsL-aHzRLfPlFtVva2NsJa5PhpC9pldhSI6AszOn2i8ClRgrWlRSg==",
    "X-Amzn-Trace-Id": "Root=1-59ecfbda-57d3b1835380fd7141457a9e",
    "x-api-key": "jNzW5AoYra3JcFlaouDuy2A1DqZTx02WRMYkhixc",
    "X-Forwarded-For": "92.4.117.116, 216.137.62.69",
    "X-Forwarded-Port": "443",
    "X-Forwarded-Proto": "https"
  },
  "queryStringParameters": {
    "station": "drsc",
    "minutes": "120"
  },
  "pathParameters": null,
  "stageVariables": null,
  "requestContext": {
    "path": "/dev/latest",
    "accountId": "151526702082",
    "resourceId": "6wzxtg",
    "stage": "dev",
    "requestId": "6f6eed45-b765-11e7-b561-d19a45380156",
    "identity": {
      "cognitoIdentityPoolId": null,
      "accountId": null,
      "cognitoIdentityId": null,
      "caller": null,
      "apiKey": "jNzW5AoYra3JcFlaouDuy2A1DqZTx02WRMYkhixc",
      "sourceIp": "92.4.117.116",
      "accessKey": null,
      "cognitoAuthenticationType": null,
      "cognitoAuthenticationProvider": null,
      "userArn": null,
      "userAgent":
        "Mozilla/5.0 (Macintosh; Intel Mac OS X 10_12_6) AppleWebKit/537.36 (KHTML, like Gecko) Chrome/61.0.3163.100 Safari/537.36",
      "user": null
    },
    "resourcePath": "/latest",
    "httpMethod": "GET",
    "apiId": "jqs5f5wrsh"
  },
  "body": null,
  "isBase64Encoded": false
}
